dks/__init__.py
dks/base/__init__.py
dks/base/activation_getter.py
dks/base/activation_transform.py
dks/base/roots_100000.npy
dks/examples/__init__.py
dks/examples/haiku/__init__.py
dks/examples/haiku/modified_resnet.py
dks/jax/__init__.py
dks/jax/activation_transform.py
dks/jax/data_preprocessing.py
dks/jax/haiku_initializers.py
dks/jax/parameter_sampling_functions.py
dks/pytorch/__init__.py
dks/pytorch/activation_transform.py
dks/pytorch/data_preprocessing.py
dks/pytorch/parameter_sampling_functions.py
dks/tensorflow/__init__.py
dks/tensorflow/activation_transform.py
dks/tensorflow/data_preprocessing.py
dks/tensorflow/parameter_sampling_functions.py
dks-0.1.2.dist-info/LICENSE
dks-0.1.2.dist-info/METADATA
dks-0.1.2.dist-info/WHEEL
dks-0.1.2.dist-info/top_level.txt
dks-0.1.2.dist-info/RECORD
