Metadata-Version: 2.1
Name: dks
Version: 0.1.2
Summary: A Python library implementing the DKS/TAT neural network transformation method.
Home-page: https://github.com/deepmind/dks
Author: DeepMind
Author-email: dks-dev@google.com
License: Apache 2.0
Classifier: Development Status :: 4 - Beta
Classifier: Intended Audience :: Developers
Classifier: Intended Audience :: Education
Classifier: Intended Audience :: Science/Research
Classifier: License :: OSI Approved :: Apache Software License
Classifier: Programming Language :: Python :: 3
Classifier: Programming Language :: Python :: 3.7
Classifier: Programming Language :: Python :: 3.8
Classifier: Programming Language :: Python :: 3.9
Classifier: Topic :: Scientific/Engineering :: Artificial Intelligence
Classifier: Topic :: Scientific/Engineering :: Mathematics
Classifier: Topic :: Software Development :: Libraries
Classifier: Topic :: Software Development :: Libraries :: Python Modules
License-File: LICENSE
Requires-Dist: numpy (>=1.16.0)
Requires-Dist: scipy (>=1.2.1)
Requires-Dist: autograd (>=1.3)
Provides-Extra: jax
Requires-Dist: dm-haiku (>=0.0.5) ; extra == 'jax'
Requires-Dist: jax (>=0.2.28) ; extra == 'jax'
Requires-Dist: jaxlib (>=0.1.74) ; extra == 'jax'
Provides-Extra: pytorch
Requires-Dist: torch (>=1.8.0) ; extra == 'pytorch'
Provides-Extra: tests
Requires-Dist: pytest-xdist ; extra == 'tests'
Requires-Dist: numpy (==1.21.5) ; extra == 'tests'
Requires-Dist: scipy (==1.7.3) ; extra == 'tests'
Requires-Dist: autograd (==1.3) ; extra == 'tests'
Requires-Dist: absl-py (==0.15.0) ; extra == 'tests'
Requires-Dist: dm-tree (==0.1.6) ; extra == 'tests'
Requires-Dist: dm-haiku (==0.0.5) ; extra == 'tests'
Requires-Dist: jax (==0.2.28) ; extra == 'tests'
Requires-Dist: jaxlib (==0.1.74) ; extra == 'tests'
Requires-Dist: tensorflow (==2.7.0) ; extra == 'tests'
Requires-Dist: torch (==1.13.1) ; extra == 'tests'
Provides-Extra: tf
Requires-Dist: tensorflow (>=1.15) ; extra == 'tf'
